{
  "updated_at": "2026-07-13T09:31:22",
  "count": 80,
  "stocks": [
    {
      "symbol": "TSM",
      "name": "台積電 ADR",
      "current": 434.11,
      "price_10d": 434.99,
      "change_10d": -0.2,
      "price_20d": 407.8,
      "change_20d": 6.45,
      "ma10": 443.58,
      "ma10_5pct": 421.4,
      "status": "觀察中",
      "alert": "OBS",
      "dist_ma10": -2.13,
      "rsi": 42.3,
      "day_high": 439.66,
      "day_low": 428.1,
      "vol_today": 9573500,
      "vol_avg": 13507228,
      "vol_ratio": 0.71,
      "w52_high": 477.57,
      "w52_low": 224.84,
      "pe": 37.75,
      "mkt_cap": "2.25T",
      "day1_price": 436.96,
      "day1_change": -0.0,
      "day2_price": 436.98,
      "day2_change": 1.02,
      "day3_price": 432.57,
      "day3_change": -4.25,
      "day4_price": 451.79,
      "day4_change": 4.06,
      "day5_price": 434.16,
      "day5_change": -2.27,
      "day6_price": 444.23,
      "day6_change": -6.98,
      "day7_price": 477.57,
      "day7_change": 4.94,
      "updated_at": "2026-07-13T09:31:22"
    },
    {
      "symbol": "GOOGL",
      "name": "Alphabet",
      "current": 357.18,
      "price_10d": 343.71,
      "change_10d": 3.92,
      "price_20d": 356.38,
      "change_20d": 0.22,
      "ma10": 358.1,
      "ma10_5pct": 340.19,
      "status": "觀察中",
      "alert": "OBS",
      "dist_ma10": -0.26,
      "rsi": 42.5,
      "day_high": 357.82,
      "day_low": 352.75,
      "vol_today": 18126000,
      "vol_avg": 34671025,
      "vol_ratio": 0.52,
      "w52_high": 402.38,
      "w52_low": 179.68,
      "pe": 27.24,
      "mkt_cap": "4.36T",
      "day1_price": 358.89,
      "day1_change": -0.84,
      "day2_price": 361.92,
      "day2_change": -1.39,
      "day3_price": 367.03,
      "day3_change": 0.16,
      "day4_price": 366.46,
      "day4_change": 1.82,
      "day5_price": 359.91,
      "day5_change": -0.36,
      "day6_price": 361.21,
      "day6_change": 1.07,
      "day7_price": 357.37,
      "day7_change": 1.05,
      "updated_at": "2026-07-13T09:31:22"
    },
    {
      "symbol": "AAPL",
      "name": "Apple",
      "current": 315.32,
      "price_10d": 275.15,
      "change_10d": 14.6,
      "price_20d": 291.58,
      "change_20d": 8.14,
      "ma10": 302.61,
      "ma10_5pct": 287.48,
      "status": "觀察中",
      "alert": "OBS",
      "dist_ma10": 4.2,
      "rsi": 61.9,
      "day_high": 316.91,
      "day_low": 312.17,
      "vol_today": 34109200,
      "vol_avg": 59653371,
      "vol_ratio": 0.57,
      "w52_high": 316.22,
      "w52_low": 201.58,
      "pe": 38.17,
      "mkt_cap": "4.63T",
      "day1_price": 316.22,
      "day1_change": 0.9,
      "day2_price": 313.39,
      "day2_change": 0.88,
      "day3_price": 310.66,
      "day3_change": -0.64,
      "day4_price": 312.66,
      "day4_change": 1.31,
      "day5_price": 308.63,
      "day5_change": 4.84,
      "day6_price": 294.38,
      "day6_change": 1.73,
      "day7_price": 289.36,
      "day7_change": 2.7,
      "updated_at": "2026-07-13T09:31:22"
    },
    {
      "symbol": "NVDA",
      "name": "NVIDIA",
      "current": 210.96,
      "price_10d": 195.74,
      "change_10d": 7.78,
      "price_20d": 200.42,
      "change_20d": 5.26,
      "ma10": 199.03,
      "ma10_5pct": 189.08,
      "status": "觀察中",
      "alert": "OBS",
      "dist_ma10": 5.99,
      "rsi": 50.3,
      "day_high": 211.0,
      "day_low": 201.92,
      "vol_today": 148124000,
      "vol_avg": 163380748,
      "vol_ratio": 0.91,
      "w52_high": 235.47,
      "w52_low": 163.85,
      "pe": 32.26,
      "mkt_cap": "5.11T",
      "day1_price": 202.78,
      "day1_change": -0.66,
      "day2_price": 204.12,
      "day2_change": 3.65,
      "day3_price": 196.93,
      "day3_change": 0.71,
      "day4_price": 195.55,
      "day4_change": 0.37,
      "day5_price": 194.83,
      "day5_change": -1.39,
      "day6_price": 197.58,
      "day6_change": -1.25,
      "day7_price": 200.09,
      "day7_change": 2.63,
      "updated_at": "2026-07-13T09:31:22"
    },
    {
      "symbol": "TSLA",
      "name": "Tesla",
      "current": 407.76,
      "price_10d": 375.12,
      "change_10d": 8.7,
      "price_20d": 381.59,
      "change_20d": 6.86,
      "ma10": 406.19,
      "ma10_5pct": 385.88,
      "status": "觀察中",
      "alert": "OBS",
      "dist_ma10": 0.39,
      "rsi": 52.0,
      "day_high": 413.16,
      "day_low": 402.81,
      "vol_today": 33342700,
      "vol_avg": 46171754,
      "vol_ratio": 0.72,
      "w52_high": 489.88,
      "w52_low": 302.63,
      "pe": 370.69,
      "mkt_cap": "1.53T",
      "day1_price": 406.55,
      "day1_change": 3.17,
      "day2_price": 394.06,
      "day2_change": -2.19,
      "day3_price": 402.9,
      "day3_change": -4.02,
      "day4_price": 419.77,
      "day4_change": 6.69,
      "day5_price": 393.45,
      "day5_change": -7.49,
      "day6_price": 425.3,
      "day6_change": 1.12,
      "day7_price": 420.6,
      "day7_change": 2.13,
      "updated_at": "2026-07-13T09:31:22"
    },
    {
      "symbol": "PLTR",
      "name": "Palantir",
      "current": 126.79,
      "price_10d": 107.27,
      "change_10d": 18.2,
      "price_20d": 130.21,
      "change_20d": -2.63,
      "ma10": 125.53,
      "ma10_5pct": 119.25,
      "status": "觀察中",
      "alert": "OBS",
      "dist_ma10": 1.0,
      "rsi": 48.5,
      "day_high": 132.28,
      "day_low": 125.77,
      "vol_today": 31097600,
      "vol_avg": 42967434,
      "vol_ratio": 0.72,
      "w52_high": 207.18,
      "w52_low": 107.27,
      "pe": 142.46,
      "mkt_cap": "304.0B",
      "day1_price": 129.04,
      "day1_change": -2.41,
      "day2_price": 132.22,
      "day2_change": -1.6,
      "day3_price": 134.37,
      "day3_change": 1.38,
      "day4_price": 132.54,
      "day4_change": 2.51,
      "day5_price": 129.3,
      "day5_change": 2.84,
      "day6_price": 125.73,
      "day6_change": 7.77,
      "day7_price": 116.67,
      "day7_change": 0.84,
      "updated_at": "2026-07-13T09:31:22"
    },
    {
      "symbol": "META",
      "name": "Meta Platforms",
      "current": 669.21,
      "price_10d": 542.87,
      "change_10d": 23.27,
      "price_20d": 570.45,
      "change_20d": 17.31,
      "ma10": 599.16,
      "ma10_5pct": 569.2,
      "status": "觀察中",
      "alert": "OBS",
      "dist_ma10": 11.69,
      "rsi": 68.7,
      "day_high": 677.86,
      "day_low": 658.01,
      "vol_today": 40563100,
      "vol_avg": 19711120,
      "vol_ratio": 2.06,
      "w52_high": 787.42,
      "w52_low": 525.23,
      "pe": 24.33,
      "mkt_cap": "1.70T",
      "day1_price": 631.48,
      "day1_change": 4.7,
      "day2_price": 603.12,
      "day2_change": -2.02,
      "day3_price": 615.58,
      "day3_change": 2.55,
      "day4_price": 600.29,
      "day4_change": 2.98,
      "day5_price": 582.9,
      "day5_change": -4.9,
      "day6_price": 612.91,
      "day6_change": 8.81,
      "day7_price": 563.29,
      "day7_change": 0.12,
      "updated_at": "2026-07-13T09:31:22"
    },
    {
      "symbol": "MSFT",
      "name": "Microsoft",
      "current": 385.1,
      "price_10d": 352.83,
      "change_10d": 9.15,
      "price_20d": 397.36,
      "change_20d": -3.09,
      "ma10": 381.77,
      "ma10_5pct": 362.68,
      "status": "觀察中",
      "alert": "OBS",
      "dist_ma10": 0.87,
      "rsi": 52.9,
      "day_high": 391.91,
      "day_low": 381.5,
      "vol_today": 24612200,
      "vol_avg": 43456768,
      "vol_ratio": 0.57,
      "w52_high": 538.66,
      "w52_low": 352.83,
      "pe": 22.94,
      "mkt_cap": "2.86T",
      "day1_price": 384.36,
      "day1_change": 0.27,
      "day2_price": 383.34,
      "day2_change": -1.41,
      "day3_price": 388.84,
      "day3_change": 0.54,
      "day4_price": 386.74,
      "day4_change": -0.96,
      "day5_price": 390.49,
      "day5_change": 1.62,
      "day6_price": 384.28,
      "day6_change": 3.02,
      "day7_price": 373.02,
      "day7_change": 1.21,
      "updated_at": "2026-07-13T09:31:22"
    },
    {
      "symbol": "INTC",
      "name": "Intel",
      "current": 109.84,
      "price_10d": 132.87,
      "change_10d": -17.33,
      "price_20d": 107.04,
      "change_20d": 2.62,
      "ma10": 121.22,
      "ma10_5pct": 115.16,
      "status": "觸發加碼",
      "alert": "Alert",
      "dist_ma10": -9.39,
      "rsi": 33.1,
      "day_high": 110.85,
      "day_low": 107.45,
      "vol_today": 70619700,
      "vol_avg": 124001968,
      "vol_ratio": 0.57,
      "w52_high": 140.94,
      "w52_low": 19.31,
      "pe": null,
      "mkt_cap": "552.1B",
      "day1_price": 112.54,
      "day1_change": 2.09,
      "day2_price": 110.24,
      "day2_change": -0.14,
      "day3_price": 110.39,
      "day3_change": -9.66,
      "day4_price": 122.2,
      "day4_change": 1.54,
      "day5_price": 120.35,
      "day5_change": -5.25,
      "day6_price": 127.02,
      "day6_change": -9.03,
      "day7_price": 139.63,
      "day7_change": 6.01,
      "updated_at": "2026-07-13T09:31:22"
    },
    {
      "symbol": "MU",
      "name": "Micron Technology",
      "current": 979.3,
      "price_10d": 1213.37,
      "change_10d": -19.29,
      "price_20d": 891.74,
      "change_20d": 9.82,
      "ma10": 1028.18,
      "ma10_5pct": 976.77,
      "status": "觸發加碼",
      "alert": "OBS",
      "dist_ma10": -4.75,
      "rsi": 40.4,
      "day_high": 998.0,
      "day_low": 954.13,
      "vol_today": 31563700,
      "vol_avg": 54548205,
      "vol_ratio": 0.58,
      "w52_high": 1213.37,
      "w52_low": 104.71,
      "pe": 22.13,
      "mkt_cap": "1.11T",
      "day1_price": 991.64,
      "day1_change": 4.52,
      "day2_price": 948.8,
      "day2_change": 1.11,
      "day3_price": 938.38,
      "day3_change": -4.71,
      "day4_price": 984.75,
      "day4_change": 0.96,
      "day5_price": 975.41,
      "day5_change": -5.49,
      "day6_price": 1032.12,
      "day6_change": -10.57,
      "day7_price": 1154.11,
      "day7_change": 0.79,
      "updated_at": "2026-07-13T09:31:22"
    },
    {
      "symbol": "ASX",
      "name": "ASX",
      "current": 42.66,
      "price_10d": 41.43,
      "change_10d": 2.97,
      "price_20d": 33.96,
      "change_20d": 25.62,
      "ma10": 41.9,
      "ma10_5pct": 39.8,
      "status": "觀察中",
      "alert": "OBS",
      "dist_ma10": 1.81,
      "rsi": 54.4,
      "day_high": 43.05,
      "day_low": 41.32,
      "vol_today": 6759300,
      "vol_avg": 12240742,
      "vol_ratio": 0.55,
      "w52_high": 44.67,
      "w52_low": 9.41,
      "pe": 66.66,
      "mkt_cap": "93.6B",
      "day1_price": 43.25,
      "day1_change": 8.31,
      "day2_price": 39.93,
      "day2_change": 0.71,
      "day3_price": 39.65,
      "day3_change": -8.47,
      "day4_price": 43.32,
      "day4_change": 4.51,
      "day5_price": 41.45,
      "day5_change": -2.61,
      "day6_price": 42.56,
      "day6_change": -4.72,
      "day7_price": 44.67,
      "day7_change": 7.1,
      "updated_at": "2026-07-13T09:31:22"
    },
    {
      "symbol": "AMZN",
      "name": "Amazon",
      "current": 245.34,
      "price_10d": 227.01,
      "change_10d": 8.07,
      "price_20d": 238.0,
      "change_20d": 3.08,
      "ma10": 242.17,
      "ma10_5pct": 230.06,
      "status": "觀察中",
      "alert": "OBS",
      "dist_ma10": 1.31,
      "rsi": 50.9,
      "day_high": 251.03,
      "day_low": 244.41,
      "vol_today": 31624900,
      "vol_avg": 53383594,
      "vol_ratio": 0.59,
      "w52_high": 274.99,
      "w52_low": 198.79,
      "pe": 29.31,
      "mkt_cap": "2.64T",
      "day1_price": 247.04,
      "day1_change": 1.4,
      "day2_price": 243.62,
      "day2_change": -0.96,
      "day3_price": 245.98,
      "day3_change": 0.75,
      "day4_price": 244.16,
      "day4_change": 0.61,
      "day5_price": 242.67,
      "day5_change": 0.4,
      "day6_price": 241.7,
      "day6_change": 1.41,
      "day7_price": 238.34,
      "day7_change": -0.75,
      "updated_at": "2026-07-13T09:31:22"
    },
    {
      "symbol": "LLY",
      "name": "Eli Lilly",
      "current": 1188.58,
      "price_10d": 1127.69,
      "change_10d": 5.4,
      "price_20d": 1136.37,
      "change_20d": 4.59,
      "ma10": 1210.01,
      "ma10_5pct": 1149.51,
      "status": "觀察中",
      "alert": "OBS",
      "dist_ma10": -1.77,
      "rsi": 65.5,
      "day_high": 1212.96,
      "day_low": 1178.32,
      "vol_today": 2009100,
      "vol_avg": 3243377,
      "vol_ratio": 0.62,
      "w52_high": 1235.56,
      "w52_low": 621.26,
      "pe": 42.19,
      "mkt_cap": "1.06T",
      "day1_price": 1216.95,
      "day1_change": 0.09,
      "day2_price": 1215.83,
      "day2_change": -1.6,
      "day3_price": 1235.56,
      "day3_change": 2.96,
      "day4_price": 1200.06,
      "day4_change": -1.14,
      "day5_price": 1213.91,
      "day5_change": 1.86,
      "day6_price": 1191.74,
      "day6_change": -0.64,
      "day7_price": 1199.43,
      "day7_change": -2.48,
      "updated_at": "2026-07-13T09:31:22"
    },
    {
      "symbol": "ASML",
      "name": "ASML Holding",
      "current": 1797.32,
      "price_10d": 1841.18,
      "change_10d": -2.38,
      "price_20d": 1734.19,
      "change_20d": 3.64,
      "ma10": 1822.21,
      "ma10_5pct": 1731.1,
      "status": "觀察中",
      "alert": "OBS",
      "dist_ma10": -1.37,
      "rsi": 42.7,
      "day_high": 1815.18,
      "day_low": 1766.66,
      "vol_today": 1216800,
      "vol_avg": 2010722,
      "vol_ratio": 0.61,
      "w52_high": 1989.44,
      "w52_low": 686.0,
      "pe": 60.97,
      "mkt_cap": "692.7B",
      "day1_price": 1804.25,
      "day1_change": 2.01,
      "day2_price": 1768.65,
      "day2_change": 1.22,
      "day3_price": 1747.28,
      "day3_change": -4.26,
      "day4_price": 1825.07,
      "day4_change": 3.15,
      "day5_price": 1769.32,
      "day5_change": -4.0,
      "day6_price": 1843.04,
      "day6_change": -7.36,
      "day7_price": 1989.44,
      "day7_change": 5.65,
      "updated_at": "2026-07-13T09:31:22"
    },
    {
      "symbol": "LRCX",
      "name": "Lam Research",
      "current": 350.33,
      "price_10d": 401.82,
      "change_10d": -12.81,
      "price_20d": 321.57,
      "change_20d": 8.94,
      "ma10": 367.9,
      "ma10_5pct": 349.5,
      "status": "觸發加碼",
      "alert": "OBS",
      "dist_ma10": -4.78,
      "rsi": 43.6,
      "day_high": 354.73,
      "day_low": 338.13,
      "vol_today": 6886600,
      "vol_avg": 12506457,
      "vol_ratio": 0.55,
      "w52_high": 433.33,
      "w52_low": 94.32,
      "pe": 66.22,
      "mkt_cap": "438.1B",
      "day1_price": 353.17,
      "day1_change": 6.01,
      "day2_price": 333.15,
      "day2_change": 2.15,
      "day3_price": 326.13,
      "day3_change": -6.87,
      "day4_price": 350.2,
      "day4_change": -0.34,
      "day5_price": 351.41,
      "day5_change": -10.19,
      "day6_price": 391.26,
      "day6_change": -9.71,
      "day7_price": 433.33,
      "day7_change": 5.46,
      "updated_at": "2026-07-13T09:31:22"
    },
    {
      "symbol": "AVGO",
      "name": "Broadcom",
      "current": 399.97,
      "price_10d": 378.91,
      "change_10d": 5.56,
      "price_20d": 371.51,
      "change_20d": 7.66,
      "ma10": 377.95,
      "ma10_5pct": 359.05,
      "status": "觀察中",
      "alert": "OBS",
      "dist_ma10": 5.83,
      "rsi": 45.8,
      "day_high": 402.44,
      "day_low": 395.7,
      "vol_today": 14582400,
      "vol_avg": 31321362,
      "vol_ratio": 0.47,
      "w52_high": 480.81,
      "w52_low": 272.38,
      "pe": 66.66,
      "mkt_cap": "1.90T",
      "day1_price": 401.11,
      "day1_change": 3.2,
      "day2_price": 388.69,
      "day2_change": 4.83,
      "day3_price": 370.78,
      "day3_change": -0.83,
      "day4_price": 373.9,
      "day4_change": 3.73,
      "day5_price": 360.45,
      "day5_change": -2.41,
      "day6_price": 369.34,
      "day6_change": -2.23,
      "day7_price": 377.75,
      "day7_change": 1.42,
      "updated_at": "2026-07-13T09:31:22"
    },
    {
      "symbol": "GEV",
      "name": "GE Vernova",
      "current": 1091.57,
      "price_10d": 1085.47,
      "change_10d": 0.56,
      "price_20d": 866.65,
      "change_20d": 25.95,
      "ma10": 1103.69,
      "ma10_5pct": 1048.51,
      "status": "觀察中",
      "alert": "OBS",
      "dist_ma10": -1.1,
      "rsi": 48.3,
      "day_high": 1102.79,
      "day_low": 1053.99,
      "vol_today": 1737300,
      "vol_avg": 3001862,
      "vol_ratio": 0.58,
      "w52_high": 1174.86,
      "w52_low": 537.7,
      "pe": 31.95,
      "mkt_cap": "293.3B",
      "day1_price": 1075.26,
      "day1_change": 0.4,
      "day2_price": 1070.99,
      "day2_change": -0.57,
      "day3_price": 1077.08,
      "day3_change": -6.51,
      "day4_price": 1152.04,
      "day4_change": 3.5,
      "day5_price": 1113.11,
      "day5_change": -1.87,
      "day6_price": 1134.35,
      "day6_change": -3.45,
      "day7_price": 1174.86,
      "day7_change": 6.56,
      "updated_at": "2026-07-13T09:31:22"
    },
    {
      "symbol": "ETN",
      "name": "Eaton Corp",
      "current": 407.28,
      "price_10d": 419.87,
      "change_10d": -3.0,
      "price_20d": 375.46,
      "change_20d": 8.47,
      "ma10": 406.97,
      "ma10_5pct": 386.62,
      "status": "觀察中",
      "alert": "OBS",
      "dist_ma10": 0.08,
      "rsi": 45.8,
      "day_high": 411.67,
      "day_low": 401.84,
      "vol_today": 1404000,
      "vol_avg": 2442062,
      "vol_ratio": 0.57,
      "w52_high": 435.78,
      "w52_low": 313.97,
      "pe": 39.85,
      "mkt_cap": "158.1B",
      "day1_price": 405.83,
      "day1_change": 1.57,
      "day2_price": 399.56,
      "day2_change": 0.98,
      "day3_price": 395.68,
      "day3_change": -4.29,
      "day4_price": 413.42,
      "day4_change": 3.74,
      "day5_price": 398.52,
      "day5_change": -3.34,
      "day6_price": 412.31,
      "day6_change": -3.24,
      "day7_price": 426.12,
      "day7_change": 4.37,
      "updated_at": "2026-07-13T09:31:22"
    },
    {
      "symbol": "NEE",
      "name": "NextEra Energy",
      "current": 87.96,
      "price_10d": 87.7,
      "change_10d": 0.3,
      "price_20d": 85.12,
      "change_20d": 3.34,
      "ma10": 87.81,
      "ma10_5pct": 83.42,
      "status": "觀察中",
      "alert": "OBS",
      "dist_ma10": 0.17,
      "rsi": 55.2,
      "day_high": 87.97,
      "day_low": 87.07,
      "vol_today": 11223100,
      "vol_avg": 12405305,
      "vol_ratio": 0.9,
      "w52_high": 97.17,
      "w52_low": 68.33,
      "pe": 22.32,
      "mkt_cap": "183.4B",
      "day1_price": 87.1,
      "day1_change": -0.39,
      "day2_price": 87.44,
      "day2_change": -1.16,
      "day3_price": 88.47,
      "day3_change": 1.18,
      "day4_price": 87.44,
      "day4_change": -1.02,
      "day5_price": 88.34,
      "day5_change": 2.28,
      "day6_price": 86.37,
      "day6_change": -1.6,
      "day7_price": 87.77,
      "day7_change": -1.0,
      "updated_at": "2026-07-13T09:31:22"
    },
    {
      "symbol": "QQQ",
      "name": "Nasdaq 100 ETF",
      "current": 725.51,
      "price_10d": 716.38,
      "change_10d": 1.27,
      "price_20d": 692.93,
      "change_20d": 4.7,
      "ma10": 719.73,
      "ma10_5pct": 683.74,
      "status": "觀察中",
      "alert": "OBS",
      "dist_ma10": 0.8,
      "rsi": 44.8,
      "day_high": 726.39,
      "day_low": 717.0,
      "vol_today": 26374600,
      "vol_avg": 45871860,
      "vol_ratio": 0.57,
      "w52_high": 745.34,
      "w52_low": 551.23,
      "pe": 32.19,
      "mkt_cap": null,
      "day1_price": 723.28,
      "day1_change": 1.66,
      "day2_price": 711.44,
      "day2_change": 0.28,
      "day3_price": 709.43,
      "day3_change": -1.85,
      "day4_price": 722.82,
      "day4_change": 1.43,
      "day5_price": 712.6,
      "day5_change": -1.73,
      "day6_price": 725.17,
      "day6_change": -1.52,
      "day7_price": 736.4,
      "day7_change": 1.7,
      "updated_at": "2026-07-13T09:31:22"
    },
    {
      "symbol": "QLD",
      "name": "2x Nasdaq ETF",
      "current": 93.7,
      "price_10d": 91.77,
      "change_10d": 2.1,
      "price_20d": 86.45,
      "change_20d": 8.39,
      "ma10": 92.39,
      "ma10_5pct": 87.77,
      "status": "觀察中",
      "alert": "OBS",
      "dist_ma10": 1.42,
      "rsi": 44.1,
      "day_high": 93.94,
      "day_low": 91.52,
      "vol_today": 2847600,
      "vol_avg": 4834674,
      "vol_ratio": 0.59,
      "w52_high": 100.46,
      "w52_low": 57.12,
      "pe": 31.65,
      "mkt_cap": null,
      "day1_price": 93.14,
      "day1_change": 3.33,
      "day2_price": 90.14,
      "day2_change": 0.5,
      "day3_price": 89.69,
      "day3_change": -3.7,
      "day4_price": 93.14,
      "day4_change": 2.79,
      "day5_price": 90.61,
      "day5_change": -3.5,
      "day6_price": 93.9,
      "day6_change": -2.96,
      "day7_price": 96.76,
      "day7_change": 3.29,
      "updated_at": "2026-07-13T09:31:22"
    },
    {
      "symbol": "VOO",
      "name": "S&P 500 ETF",
      "current": 693.86,
      "price_10d": 673.75,
      "change_10d": 2.98,
      "price_20d": 665.11,
      "change_20d": 4.32,
      "ma10": 685.59,
      "ma10_5pct": 651.31,
      "status": "觀察中",
      "alert": "OBS",
      "dist_ma10": 1.21,
      "rsi": 57.2,
      "day_high": 694.33,
      "day_low": 687.63,
      "vol_today": 5318000,
      "vol_avg": 9776791,
      "vol_ratio": 0.54,
      "w52_high": 696.23,
      "w52_low": 564.78,
      "pe": 27.08,
      "mkt_cap": null,
      "day1_price": 690.69,
      "day1_change": 0.79,
      "day2_price": 685.26,
      "day2_change": -0.26,
      "day3_price": 687.08,
      "day3_change": -0.51,
      "day4_price": 690.62,
      "day4_change": 0.84,
      "day5_price": 684.84,
      "day5_change": -0.09,
      "day6_price": 685.46,
      "day6_change": -0.2,
      "day7_price": 686.81,
      "day7_change": 0.85,
      "updated_at": "2026-07-13T09:31:22"
    },
    {
      "symbol": "SSO",
      "name": "2x S&P 500 ETF",
      "current": 68.72,
      "price_10d": 65.05,
      "change_10d": 5.64,
      "price_20d": 63.55,
      "change_20d": 8.14,
      "ma10": 67.19,
      "ma10_5pct": 63.83,
      "status": "觀察中",
      "alert": "OBS",
      "dist_ma10": 2.28,
      "rsi": 56.0,
      "day_high": 68.83,
      "day_low": 67.52,
      "vol_today": 2337300,
      "vol_avg": 3529062,
      "vol_ratio": 0.66,
      "w52_high": 69.83,
      "w52_low": 48.77,
      "pe": 27.41,
      "mkt_cap": null,
      "day1_price": 68.17,
      "day1_change": 1.7,
      "day2_price": 67.03,
      "day2_change": -0.68,
      "day3_price": 67.49,
      "day3_change": -0.98,
      "day4_price": 68.16,
      "day4_change": 1.73,
      "day5_price": 67.0,
      "day5_change": -0.31,
      "day6_price": 67.21,
      "day6_change": -0.25,
      "day7_price": 67.38,
      "day7_change": 1.55,
      "updated_at": "2026-07-13T09:31:22"
    },
    {
      "symbol": "LEU",
      "name": "Centrus Energy",
      "current": 171.05,
      "price_10d": 170.38,
      "change_10d": 0.39,
      "price_20d": 146.61,
      "change_20d": 16.67,
      "ma10": 167.31,
      "ma10_5pct": 158.94,
      "status": "觀察中",
      "alert": "OBS",
      "dist_ma10": 2.24,
      "rsi": 36.6,
      "day_high": 177.32,
      "day_low": 170.2,
      "vol_today": 638900,
      "vol_avg": 863288,
      "vol_ratio": 0.74,
      "w52_high": 436.0,
      "w52_low": 146.61,
      "pe": 62.2,
      "mkt_cap": "3.4B",
      "day1_price": 173.56,
      "day1_change": 4.26,
      "day2_price": 166.47,
      "day2_change": 0.5,
      "day3_price": 165.64,
      "day3_change": -4.93,
      "day4_price": 174.23,
      "day4_change": 7.46,
      "day5_price": 162.13,
      "day5_change": -2.53,
      "day6_price": 166.34,
      "day6_change": -0.91,
      "day7_price": 167.87,
      "day7_change": 4.76,
      "updated_at": "2026-07-13T09:31:22"
    },
    {
      "symbol": "ORCL",
      "name": "Oracle",
      "current": 140.64,
      "price_10d": 151.93,
      "change_10d": -7.43,
      "price_20d": 200.56,
      "change_20d": -29.88,
      "ma10": 143.18,
      "ma10_5pct": 136.02,
      "status": "觀察中",
      "alert": "OBS",
      "dist_ma10": -1.77,
      "rsi": 12.5,
      "day_high": 145.68,
      "day_low": 139.26,
      "vol_today": 29735200,
      "vol_avg": 30340151,
      "vol_ratio": 0.98,
      "w52_high": 324.63,
      "w52_low": 135.53,
      "pe": 24.08,
      "mkt_cap": "405.1B",
      "day1_price": 143.72,
      "day1_change": 2.66,
      "day2_price": 140.0,
      "day2_change": -0.79,
      "day3_price": 141.11,
      "day3_change": -1.5,
      "day4_price": 143.26,
      "day4_change": 2.49,
      "day5_price": 139.78,
      "day5_change": -1.57,
      "day6_price": 142.01,
      "day6_change": -2.76,
      "day7_price": 146.04,
      "day7_change": -0.82,
      "updated_at": "2026-07-13T09:31:22"
    },
    {
      "symbol": "USAR",
      "name": "USAR",
      "current": 18.48,
      "price_10d": 20.66,
      "change_10d": -10.55,
      "price_20d": 20.33,
      "change_20d": -9.1,
      "ma10": 19.52,
      "ma10_5pct": 18.54,
      "status": "觸發加碼",
      "alert": "Alert",
      "dist_ma10": -5.33,
      "rsi": 21.9,
      "day_high": 19.08,
      "day_low": 18.3,
      "vol_today": 5913400,
      "vol_avg": 15200128,
      "vol_ratio": 0.39,
      "w52_high": 38.68,
      "w52_low": 10.71,
      "pe": null,
      "mkt_cap": "4.5B",
      "day1_price": 18.87,
      "day1_change": 2.28,
      "day2_price": 18.45,
      "day2_change": 3.77,
      "day3_price": 17.78,
      "day3_change": -8.11,
      "day4_price": 19.35,
      "day4_change": 1.04,
      "day5_price": 19.15,
      "day5_change": -4.15,
      "day6_price": 19.98,
      "day6_change": -7.41,
      "day7_price": 21.58,
      "day7_change": 2.57,
      "updated_at": "2026-07-13T09:31:22"
    },
    {
      "symbol": "UUUU",
      "name": "Energy Fuels",
      "current": 13.58,
      "price_10d": 14.42,
      "change_10d": -5.83,
      "price_20d": 13.69,
      "change_20d": -0.8,
      "ma10": 13.86,
      "ma10_5pct": 13.17,
      "status": "觀察中",
      "alert": "OBS",
      "dist_ma10": -2.02,
      "rsi": 19.1,
      "day_high": 14.23,
      "day_low": 13.47,
      "vol_today": 7054300,
      "vol_avg": 10148848,
      "vol_ratio": 0.7,
      "w52_high": 27.72,
      "w52_low": 6.6,
      "pe": null,
      "mkt_cap": "3.4B",
      "day1_price": 13.49,
      "day1_change": 2.66,
      "day2_price": 13.14,
      "day2_change": 2.18,
      "day3_price": 12.86,
      "day3_change": -6.61,
      "day4_price": 13.77,
      "day4_change": -0.29,
      "day5_price": 13.81,
      "day5_change": -2.88,
      "day6_price": 14.22,
      "day6_change": -1.93,
      "day7_price": 14.5,
      "day7_change": -0.62,
      "updated_at": "2026-07-13T09:31:22"
    },
    {
      "symbol": "GLD",
      "name": "SPDR Gold ETF",
      "current": 377.01,
      "price_10d": 369.46,
      "change_10d": 2.04,
      "price_20d": 374.58,
      "change_20d": 0.65,
      "ma10": 374.86,
      "ma10_5pct": 356.12,
      "status": "觀察中",
      "alert": "OBS",
      "dist_ma10": 0.57,
      "rsi": 41.6,
      "day_high": 377.55,
      "day_low": 373.7,
      "vol_today": 5453000,
      "vol_avg": 7413685,
      "vol_ratio": 0.74,
      "w52_high": 495.9,
      "w52_low": 300.96,
      "pe": null,
      "mkt_cap": null,
      "day1_price": 378.18,
      "day1_change": 1.0,
      "day2_price": 374.45,
      "day2_change": -0.81,
      "day3_price": 377.49,
      "day3_change": -1.21,
      "day4_price": 382.13,
      "day4_change": 1.06,
      "day5_price": 378.13,
      "day5_change": 2.03,
      "day6_price": 370.6,
      "day6_change": 0.6,
      "day7_price": 368.38,
      "day7_change": -0.05,
      "updated_at": "2026-07-13T09:31:22"
    },
    {
      "symbol": "B",
      "name": "Barnes Group",
      "current": 36.68,
      "price_10d": 36.75,
      "change_10d": -0.19,
      "price_20d": 37.19,
      "change_20d": -1.37,
      "ma10": 36.98,
      "ma10_5pct": 35.13,
      "status": "觀察中",
      "alert": "OBS",
      "dist_ma10": -0.81,
      "rsi": 33.4,
      "day_high": 36.91,
      "day_low": 36.25,
      "vol_today": 4637400,
      "vol_avg": 11616402,
      "vol_ratio": 0.4,
      "w52_high": 52.32,
      "w52_low": 20.27,
      "pe": 10.08,
      "mkt_cap": "61.6B",
      "day1_price": 36.83,
      "day1_change": 3.05,
      "day2_price": 35.74,
      "day2_change": -3.04,
      "day3_price": 36.86,
      "day3_change": -3.28,
      "day4_price": 38.11,
      "day4_change": -0.26,
      "day5_price": 38.21,
      "day5_change": 4.83,
      "day6_price": 36.45,
      "day6_change": -0.76,
      "day7_price": 36.73,
      "day7_change": -0.54,
      "updated_at": "2026-07-13T09:31:22"
    },
    {
      "symbol": "AEM",
      "name": "Agnico Eagle",
      "current": 146.87,
      "price_10d": 156.18,
      "change_10d": -5.96,
      "price_20d": 152.48,
      "change_20d": -3.68,
      "ma10": 152.09,
      "ma10_5pct": 144.49,
      "status": "觀察中",
      "alert": "OBS",
      "dist_ma10": -3.43,
      "rsi": 25.8,
      "day_high": 149.22,
      "day_low": 145.44,
      "vol_today": 1724900,
      "vol_avg": 2788602,
      "vol_ratio": 0.62,
      "w52_high": 251.57,
      "w52_low": 116.64,
      "pe": 13.83,
      "mkt_cap": "73.4B",
      "day1_price": 149.03,
      "day1_change": 2.86,
      "day2_price": 144.89,
      "day2_change": -3.62,
      "day3_price": 150.33,
      "day3_change": -2.98,
      "day4_price": 154.94,
      "day4_change": 0.7,
      "day5_price": 153.86,
      "day5_change": -0.64,
      "day6_price": 154.85,
      "day6_change": -0.18,
      "day7_price": 155.13,
      "day7_change": 0.89,
      "updated_at": "2026-07-13T09:31:22"
    },
    {
      "symbol": "COHR",
      "name": "Coherent Corp",
      "current": 324.5,
      "price_10d": 407.25,
      "change_10d": -20.32,
      "price_20d": 354.77,
      "change_20d": -8.53,
      "ma10": 348.69,
      "ma10_5pct": 331.26,
      "status": "觸發加碼",
      "alert": "Alert",
      "dist_ma10": -6.94,
      "rsi": 36.9,
      "day_high": 330.15,
      "day_low": 315.19,
      "vol_today": 4025800,
      "vol_avg": 5723485,
      "vol_ratio": 0.7,
      "w52_high": 426.89,
      "w52_low": 86.55,
      "pe": 153.79,
      "mkt_cap": "63.5B",
      "day1_price": 327.24,
      "day1_change": 3.21,
      "day2_price": 317.05,
      "day2_change": 0.93,
      "day3_price": 314.13,
      "day3_change": -6.43,
      "day4_price": 335.7,
      "day4_change": 0.7,
      "day5_price": 333.36,
      "day5_change": -9.57,
      "day6_price": 368.65,
      "day6_change": -6.55,
      "day7_price": 394.47,
      "day7_change": 0.83,
      "updated_at": "2026-07-13T09:31:22"
    },
    {
      "symbol": "LITE",
      "name": "Lumentum",
      "current": 802.01,
      "price_10d": 861.97,
      "change_10d": -6.96,
      "price_20d": 853.26,
      "change_20d": -6.01,
      "ma10": 778.1,
      "ma10_5pct": 739.19,
      "status": "觀察中",
      "alert": "OBS",
      "dist_ma10": 3.07,
      "rsi": 45.2,
      "day_high": 806.56,
      "day_low": 761.62,
      "vol_today": 3669900,
      "vol_avg": 5522602,
      "vol_ratio": 0.66,
      "w52_high": 1053.09,
      "w52_low": 92.24,
      "pe": 140.95,
      "mkt_cap": "62.4B",
      "day1_price": 785.77,
      "day1_change": 11.13,
      "day2_price": 707.1,
      "day2_change": 1.17,
      "day3_price": 698.91,
      "day3_change": -4.42,
      "day4_price": 731.25,
      "day4_change": 0.4,
      "day5_price": 728.32,
      "day5_change": -9.09,
      "day6_price": 801.16,
      "day6_change": -6.63,
      "day7_price": 858.06,
      "day7_change": 0.78,
      "updated_at": "2026-07-13T09:31:22"
    },
    {
      "symbol": "APLD",
      "name": "Applied Digital",
      "current": 31.15,
      "price_10d": 40.95,
      "change_10d": -23.93,
      "price_20d": 38.92,
      "change_20d": -19.96,
      "ma10": 34.19,
      "ma10_5pct": 32.48,
      "status": "觸發加碼",
      "alert": "Alert",
      "dist_ma10": -8.89,
      "rsi": 10.7,
      "day_high": 32.2,
      "day_low": 30.59,
      "vol_today": 12337600,
      "vol_avg": 21160282,
      "vol_ratio": 0.58,
      "w52_high": 49.65,
      "w52_low": 9.18,
      "pe": null,
      "mkt_cap": "8.9B",
      "day1_price": 32.29,
      "day1_change": 2.7,
      "day2_price": 31.44,
      "day2_change": 2.38,
      "day3_price": 30.71,
      "day3_change": -8.33,
      "day4_price": 33.5,
      "day4_change": 1.33,
      "day5_price": 33.06,
      "day5_change": -6.93,
      "day6_price": 35.52,
      "day6_change": -4.77,
      "day7_price": 37.3,
      "day7_change": -1.24,
      "updated_at": "2026-07-13T09:31:22"
    },
    {
      "symbol": "CRWD",
      "name": "CrowdStrike",
      "current": 187.18,
      "price_10d": 169.66,
      "change_10d": 10.33,
      "price_20d": 161.93,
      "change_20d": 15.59,
      "ma10": 190.96,
      "ma10_5pct": 181.41,
      "status": "觀察中",
      "alert": "OBS",
      "dist_ma10": -1.98,
      "rsi": 62.6,
      "day_high": 198.0,
      "day_low": 186.48,
      "vol_today": 9252800,
      "vol_avg": 13178388,
      "vol_ratio": 0.7,
      "w52_high": 199.38,
      "w52_low": 87.56,
      "pe": null,
      "mkt_cap": "190.6B",
      "day1_price": 198.4,
      "day1_change": 3.81,
      "day2_price": 191.12,
      "day2_change": -1.8,
      "day3_price": 194.62,
      "day3_change": -2.39,
      "day4_price": 199.38,
      "day4_change": 2.78,
      "day5_price": 193.98,
      "day5_change": 0.41,
      "day6_price": 193.18,
      "day6_change": 1.25,
      "day7_price": 190.79,
      "day7_change": 2.72,
      "updated_at": "2026-07-13T09:31:22"
    },
    {
      "symbol": "IONQ",
      "name": "IonQ",
      "current": 42.86,
      "price_10d": 50.56,
      "change_10d": -15.23,
      "price_20d": 56.63,
      "change_20d": -24.32,
      "ma10": 48.39,
      "ma10_5pct": 45.97,
      "status": "觸發加碼",
      "alert": "Alert",
      "dist_ma10": -11.43,
      "rsi": 24.0,
      "day_high": 45.45,
      "day_low": 42.4,
      "vol_today": 14477000,
      "vol_avg": 27290454,
      "vol_ratio": 0.53,
      "w52_high": 82.09,
      "w52_low": 26.59,
      "pe": 109.9,
      "mkt_cap": "16.0B",
      "day1_price": 44.77,
      "day1_change": -0.69,
      "day2_price": 45.08,
      "day2_change": -0.62,
      "day3_price": 45.36,
      "day3_change": -7.18,
      "day4_price": 48.87,
      "day4_change": -0.51,
      "day5_price": 49.12,
      "day5_change": -4.44,
      "day6_price": 51.4,
      "day6_change": -3.49,
      "day7_price": 53.26,
      "day7_change": -1.15,
      "updated_at": "2026-07-13T09:31:22"
    },
    {
      "symbol": "AMD",
      "name": "AMD",
      "current": 557.89,
      "price_10d": 532.57,
      "change_10d": 4.75,
      "price_20d": 452.4,
      "change_20d": 23.32,
      "ma10": 539.09,
      "ma10_5pct": 512.14,
      "status": "觀察中",
      "alert": "OBS",
      "dist_ma10": 3.49,
      "rsi": 53.4,
      "day_high": 560.25,
      "day_low": 540.05,
      "vol_today": 20654300,
      "vol_avg": 31036637,
      "vol_ratio": 0.67,
      "w52_high": 580.91,
      "w52_low": 146.24,
      "pe": 185.35,
      "mkt_cap": "909.7B",
      "day1_price": 546.72,
      "day1_change": 5.66,
      "day2_price": 517.41,
      "day2_change": 0.25,
      "day3_price": 516.11,
      "day3_change": -6.51,
      "day4_price": 552.05,
      "day4_change": 6.61,
      "day5_price": 517.82,
      "day5_change": -4.26,
      "day6_price": 540.88,
      "day6_change": -6.89,
      "day7_price": 580.91,
      "day7_change": 7.68,
      "updated_at": "2026-07-13T09:31:22"
    },
    {
      "symbol": "OKLO",
      "name": "Oklo",
      "current": 48.85,
      "price_10d": 51.01,
      "change_10d": -4.23,
      "price_20d": 54.02,
      "change_20d": -9.57,
      "ma10": 50.5,
      "ma10_5pct": 47.97,
      "status": "觀察中",
      "alert": "OBS",
      "dist_ma10": -3.27,
      "rsi": 22.1,
      "day_high": 50.65,
      "day_low": 47.63,
      "vol_today": 6597100,
      "vol_avg": 12266042,
      "vol_ratio": 0.54,
      "w52_high": 174.14,
      "w52_low": 45.58,
      "pe": null,
      "mkt_cap": "8.5B",
      "day1_price": 49.27,
      "day1_change": 4.21,
      "day2_price": 47.28,
      "day2_change": -1.29,
      "day3_price": 47.9,
      "day3_change": -7.6,
      "day4_price": 51.84,
      "day4_change": -0.99,
      "day5_price": 52.36,
      "day5_change": -0.17,
      "day6_price": 52.45,
      "day6_change": 0.23,
      "day7_price": 52.33,
      "day7_change": -0.82,
      "updated_at": "2026-07-13T09:31:22"
    },
    {
      "symbol": "SNOW",
      "name": "Snowflake",
      "current": 261.45,
      "price_10d": 227.06,
      "change_10d": 15.15,
      "price_20d": 239.9,
      "change_20d": 8.98,
      "ma10": 259.15,
      "ma10_5pct": 246.19,
      "status": "觀察中",
      "alert": "OBS",
      "dist_ma10": 0.89,
      "rsi": 71.9,
      "day_high": 274.93,
      "day_low": 258.34,
      "vol_today": 4139800,
      "vol_avg": 9138891,
      "vol_ratio": 0.45,
      "w52_high": 280.16,
      "w52_low": 121.11,
      "pe": null,
      "mkt_cap": "90.6B",
      "day1_price": 267.49,
      "day1_change": 2.37,
      "day2_price": 261.31,
      "day2_change": -0.54,
      "day3_price": 262.74,
      "day3_change": 0.25,
      "day4_price": 262.09,
      "day4_change": 0.75,
      "day5_price": 260.15,
      "day5_change": -0.4,
      "day6_price": 261.19,
      "day6_change": 2.63,
      "day7_price": 254.5,
      "day7_change": 1.13,
      "updated_at": "2026-07-13T09:31:22"
    },
    {
      "symbol": "VRT",
      "name": "Vertiv",
      "current": 318.86,
      "price_10d": 325.57,
      "change_10d": -2.06,
      "price_20d": 280.92,
      "change_20d": 13.51,
      "ma10": 314.23,
      "ma10_5pct": 298.52,
      "status": "觀察中",
      "alert": "OBS",
      "dist_ma10": 1.47,
      "rsi": 46.7,
      "day_high": 323.81,
      "day_low": 315.68,
      "vol_today": 2998400,
      "vol_avg": 6512468,
      "vol_ratio": 0.46,
      "w52_high": 376.15,
      "w52_low": 121.69,
      "pe": 79.91,
      "mkt_cap": "122.5B",
      "day1_price": 323.92,
      "day1_change": 1.92,
      "day2_price": 317.81,
      "day2_change": 4.0,
      "day3_price": 305.58,
      "day3_change": -4.05,
      "day4_price": 318.47,
      "day4_change": 5.97,
      "day5_price": 300.53,
      "day5_change": -3.5,
      "day6_price": 311.42,
      "day6_change": -6.99,
      "day7_price": 334.82,
      "day7_change": 9.07,
      "updated_at": "2026-07-13T09:31:22"
    },
    {
      "symbol": "NBIS",
      "name": "Nebius Group",
      "current": 219.65,
      "price_10d": 256.63,
      "change_10d": -14.41,
      "price_20d": 211.69,
      "change_20d": 3.76,
      "ma10": 228.3,
      "ma10_5pct": 216.88,
      "status": "觸發加碼",
      "alert": "OBS",
      "dist_ma10": -3.79,
      "rsi": 32.2,
      "day_high": 224.48,
      "day_low": 207.44,
      "vol_today": 11463100,
      "vol_avg": 17574577,
      "vol_ratio": 0.65,
      "w52_high": 286.69,
      "w52_low": 44.3,
      "pe": 84.81,
      "mkt_cap": "55.8B",
      "day1_price": 216.2,
      "day1_change": -0.13,
      "day2_price": 216.48,
      "day2_change": 10.91,
      "day3_price": 195.19,
      "day3_change": -8.37,
      "day4_price": 213.02,
      "day4_change": -1.21,
      "day5_price": 215.62,
      "day5_change": -5.92,
      "day6_price": 229.18,
      "day6_change": -17.01,
      "day7_price": 276.17,
      "day7_change": 5.75,
      "updated_at": "2026-07-13T09:31:22"
    },
    {
      "symbol": "UNH",
      "name": "UnitedHealth",
      "current": 424.62,
      "price_10d": 415.53,
      "change_10d": 2.19,
      "price_20d": 405.15,
      "change_20d": 4.81,
      "ma10": 424.33,
      "ma10_5pct": 403.11,
      "status": "觀察中",
      "alert": "OBS",
      "dist_ma10": 0.07,
      "rsi": 62.9,
      "day_high": 432.86,
      "day_low": 423.65,
      "vol_today": 3797100,
      "vol_avg": 6555377,
      "vol_ratio": 0.58,
      "w52_high": 431.68,
      "w52_low": 231.57,
      "pe": 31.95,
      "mkt_cap": "385.6B",
      "day1_price": 431.68,
      "day1_change": 1.43,
      "day2_price": 425.6,
      "day2_change": -0.6,
      "day3_price": 428.19,
      "day3_change": 2.44,
      "day4_price": 417.99,
      "day4_change": -1.73,
      "day5_price": 425.36,
      "day5_change": -0.28,
      "day6_price": 426.54,
      "day6_change": 2.62,
      "day7_price": 415.63,
      "day7_change": -1.0,
      "updated_at": "2026-07-13T09:31:22"
    },
    {
      "symbol": "NFLX",
      "name": "Netflix",
      "current": 73.37,
      "price_10d": 70.9,
      "change_10d": 3.48,
      "price_20d": 82.0,
      "change_20d": -10.52,
      "ma10": 74.75,
      "ma10_5pct": 71.01,
      "status": "觀察中",
      "alert": "OBS",
      "dist_ma10": -1.85,
      "rsi": 41.1,
      "day_high": 75.7,
      "day_low": 72.51,
      "vol_today": 46594700,
      "vol_avg": 42855802,
      "vol_ratio": 1.09,
      "w52_high": 127.42,
      "w52_low": 70.9,
      "pe": 23.67,
      "mkt_cap": "308.9B",
      "day1_price": 75.47,
      "day1_change": -0.16,
      "day2_price": 75.59,
      "day2_change": -0.77,
      "day3_price": 76.18,
      "day3_change": 0.21,
      "day4_price": 76.02,
      "day4_change": -2.1,
      "day5_price": 77.65,
      "day5_change": 4.66,
      "day6_price": 74.19,
      "day6_change": 3.91,
      "day7_price": 71.4,
      "day7_change": -3.23,
      "updated_at": "2026-07-13T09:31:22"
    },
    {
      "symbol": "CRWV",
      "name": "CoreWeave",
      "current": 88.88,
      "price_10d": 98.76,
      "change_10d": -10.0,
      "price_20d": 95.61,
      "change_20d": -7.04,
      "ma10": 89.76,
      "ma10_5pct": 85.27,
      "status": "觸發加碼",
      "alert": "OBS",
      "dist_ma10": -0.98,
      "rsi": 25.6,
      "day_high": 91.31,
      "day_low": 87.93,
      "vol_today": 12667300,
      "vol_avg": 29180320,
      "vol_ratio": 0.43,
      "w52_high": 148.75,
      "w52_low": 64.55,
      "pe": null,
      "mkt_cap": "48.5B",
      "day1_price": 89.7,
      "day1_change": -0.33,
      "day2_price": 90.0,
      "day2_change": 7.75,
      "day3_price": 83.53,
      "day3_change": -3.39,
      "day4_price": 86.46,
      "day4_change": 5.76,
      "day5_price": 81.75,
      "day5_change": -4.59,
      "day6_price": 85.68,
      "day6_change": -13.92,
      "day7_price": 99.54,
      "day7_change": 4.22,
      "updated_at": "2026-07-13T09:31:22"
    },
    {
      "symbol": "MRVL",
      "name": "Marvell Technology",
      "current": 235.81,
      "price_10d": 281.19,
      "change_10d": -16.14,
      "price_20d": 252.53,
      "change_20d": -6.62,
      "ma10": 254.99,
      "ma10_5pct": 242.24,
      "status": "觸發加碼",
      "alert": "Alert",
      "dist_ma10": -7.52,
      "rsi": 29.2,
      "day_high": 240.94,
      "day_low": 232.02,
      "vol_today": 15063200,
      "vol_avg": 54937271,
      "vol_ratio": 0.27,
      "w52_high": 316.35,
      "w52_low": 62.18,
      "pe": 81.31,
      "mkt_cap": "211.6B",
      "day1_price": 243.21,
      "day1_change": 4.99,
      "day2_price": 231.65,
      "day2_change": 0.44,
      "day3_price": 230.64,
      "day3_change": -7.45,
      "day4_price": 249.21,
      "day4_change": 1.62,
      "day5_price": 245.23,
      "day5_change": -9.84,
      "day6_price": 271.98,
      "day6_change": -8.68,
      "day7_price": 297.82,
      "day7_change": 7.25,
      "updated_at": "2026-07-13T09:31:22"
    },
    {
      "symbol": "2330.TW",
      "name": "台積電",
      "current": 2440.0,
      "price_10d": 2370.0,
      "change_10d": 2.95,
      "price_20d": 2310.0,
      "change_20d": 5.63,
      "ma10": 2446.0,
      "ma10_5pct": 2323.7,
      "status": "觀察中",
      "alert": "OBS",
      "dist_ma10": -0.25,
      "rsi": 45.1,
      "day_high": 2480.0,
      "day_low": 2440.0,
      "vol_today": 34539893,
      "vol_avg": 32797464,
      "vol_ratio": 1.05,
      "w52_high": 2510.0,
      "w52_low": 1080.6,
      "pe": 33.13,
      "mkt_cap": "63.27T",
      "day1_price": 2415.0,
      "day1_change": 0.0,
      "day2_price": 2415.0,
      "day2_change": -2.03,
      "day3_price": 2465.0,
      "day3_change": 1.02,
      "day4_price": 2440.0,
      "day4_change": -0.81,
      "day5_price": 2460.0,
      "day5_change": 0.61,
      "day6_price": 2445.0,
      "day6_change": -0.81,
      "day7_price": 2465.0,
      "day7_change": -1.6,
      "updated_at": "2026-07-13T09:31:22"
    },
    {
      "symbol": "3711.TW",
      "name": "日月光控股",
      "current": 670.0,
      "price_10d": 621.32,
      "change_10d": 7.83,
      "price_20d": 584.66,
      "change_20d": 14.6,
      "ma10": 675.19,
      "ma10_5pct": 641.43,
      "status": "觀察中",
      "alert": "OBS",
      "dist_ma10": -0.77,
      "rsi": 52.4,
      "day_high": 690.0,
      "day_low": 657.0,
      "vol_today": 27762583,
      "vol_avg": 25801874,
      "vol_ratio": 1.08,
      "w52_high": 720.42,
      "w52_low": 142.2,
      "pe": 65.56,
      "mkt_cap": "2.94T",
      "day1_price": 677.0,
      "day1_change": 0.0,
      "day2_price": 677.0,
      "day2_change": 8.32,
      "day3_price": 625.0,
      "day3_change": -3.99,
      "day4_price": 651.0,
      "day4_change": -4.12,
      "day5_price": 679.0,
      "day5_change": -0.44,
      "day6_price": 682.0,
      "day6_change": -5.33,
      "day7_price": 720.42,
      "day7_change": 3.42,
      "updated_at": "2026-07-13T09:31:22"
    },
    {
      "symbol": "6285.TW",
      "name": "啟碁",
      "current": 259.0,
      "price_10d": 232.09,
      "change_10d": 11.59,
      "price_20d": 265.52,
      "change_20d": -2.46,
      "ma10": 255.37,
      "ma10_5pct": 242.6,
      "status": "觀察中",
      "alert": "OBS",
      "dist_ma10": 1.42,
      "rsi": 54.9,
      "day_high": 271.5,
      "day_low": 248.0,
      "vol_today": 15125843,
      "vol_avg": 14756537,
      "vol_ratio": 1.03,
      "w52_high": 313.71,
      "w52_low": 94.41,
      "pe": 41.24,
      "mkt_cap": "125.3B",
      "day1_price": 260.5,
      "day1_change": 0.0,
      "day2_price": 260.5,
      "day2_change": 3.58,
      "day3_price": 251.5,
      "day3_change": 3.29,
      "day4_price": 243.5,
      "day4_change": -5.8,
      "day5_price": 258.5,
      "day5_change": 0.19,
      "day6_price": 258.0,
      "day6_change": 0.0,
      "day7_price": 258.0,
      "day7_change": 3.61,
      "updated_at": "2026-07-13T09:31:22"
    },
    {
      "symbol": "0050.TW",
      "name": "元大台灣50",
      "current": 106.0,
      "price_10d": 104.45,
      "change_10d": 1.48,
      "price_20d": 101.95,
      "change_20d": 3.97,
      "ma10": 107.24,
      "ma10_5pct": 101.88,
      "status": "觀察中",
      "alert": "OBS",
      "dist_ma10": -1.16,
      "rsi": 38.0,
      "day_high": 107.55,
      "day_low": 105.7,
      "vol_today": 71275584,
      "vol_avg": 112280323,
      "vol_ratio": 0.63,
      "w52_high": 111.15,
      "w52_low": 48.3,
      "pe": 30.96,
      "mkt_cap": null,
      "day1_price": 105.8,
      "day1_change": 0.0,
      "day2_price": 105.8,
      "day2_change": -0.24,
      "day3_price": 106.05,
      "day3_change": -0.14,
      "day4_price": 106.2,
      "day4_change": -1.89,
      "day5_price": 108.25,
      "day5_change": -0.09,
      "day6_price": 108.35,
      "day6_change": -0.41,
      "day7_price": 108.8,
      "day7_change": -0.5,
      "updated_at": "2026-07-13T09:31:22"
    },
    {
      "symbol": "00631L.TW",
      "name": "元大台灣50正2",
      "current": 36.86,
      "price_10d": 36.28,
      "change_10d": 1.6,
      "price_20d": 34.83,
      "change_20d": 5.83,
      "ma10": 37.91,
      "ma10_5pct": 36.01,
      "status": "觀察中",
      "alert": "OBS",
      "dist_ma10": -2.77,
      "rsi": 36.2,
      "day_high": 38.03,
      "day_low": 36.61,
      "vol_today": 203831039,
      "vol_avg": 289602804,
      "vol_ratio": 0.7,
      "w52_high": 41.32,
      "w52_low": 10.03,
      "pe": null,
      "mkt_cap": null,
      "day1_price": 36.78,
      "day1_change": 0.0,
      "day2_price": 36.78,
      "day2_change": -0.97,
      "day3_price": 37.14,
      "day3_change": -0.13,
      "day4_price": 37.19,
      "day4_change": -4.03,
      "day5_price": 38.75,
      "day5_change": -0.13,
      "day6_price": 38.8,
      "day6_change": -0.21,
      "day7_price": 38.88,
      "day7_change": -1.52,
      "updated_at": "2026-07-13T09:31:22"
    },
    {
      "symbol": "00675L.TW",
      "name": "富邦臺灣加權正2",
      "current": 319.5,
      "price_10d": 318.6,
      "change_10d": 0.28,
      "price_20d": 307.55,
      "change_20d": 3.89,
      "ma10": 331.5,
      "ma10_5pct": 314.93,
      "status": "觀察中",
      "alert": "OBS",
      "dist_ma10": -3.62,
      "rsi": 35.8,
      "day_high": 331.9,
      "day_low": 317.9,
      "vol_today": 1845498,
      "vol_avg": 2768791,
      "vol_ratio": 0.67,
      "w52_high": 364.0,
      "w52_low": 87.85,
      "pe": null,
      "mkt_cap": null,
      "day1_price": 321.0,
      "day1_change": 0.0,
      "day2_price": 321.0,
      "day2_change": -0.47,
      "day3_price": 322.5,
      "day3_change": -0.32,
      "day4_price": 323.55,
      "day4_change": -4.78,
      "day5_price": 339.8,
      "day5_change": -0.85,
      "day6_price": 342.7,
      "day6_change": 0.56,
      "day7_price": 340.8,
      "day7_change": -1.45,
      "updated_at": "2026-07-13T09:31:22"
    },
    {
      "symbol": "00662.TW",
      "name": "富邦NASDAQ",
      "current": 121.15,
      "price_10d": 120.4,
      "change_10d": 0.62,
      "price_20d": 120.05,
      "change_20d": 0.92,
      "ma10": 121.58,
      "ma10_5pct": 115.5,
      "status": "觀察中",
      "alert": "OBS",
      "dist_ma10": -0.35,
      "rsi": 48.8,
      "day_high": 122.6,
      "day_low": 121.15,
      "vol_today": 5571159,
      "vol_avg": 5337749,
      "vol_ratio": 1.04,
      "w52_high": 123.95,
      "w52_low": 85.35,
      "pe": 38.84,
      "mkt_cap": null,
      "day1_price": 120.9,
      "day1_change": 0.0,
      "day2_price": 120.9,
      "day2_change": 0.62,
      "day3_price": 120.15,
      "day3_change": -0.74,
      "day4_price": 121.05,
      "day4_change": -0.53,
      "day5_price": 121.7,
      "day5_change": 0.12,
      "day6_price": 121.55,
      "day6_change": -0.53,
      "day7_price": 122.2,
      "day7_change": -1.17,
      "updated_at": "2026-07-13T09:31:22"
    },
    {
      "symbol": "00924.TW",
      "name": "復華S&P500成長",
      "current": 32.77,
      "price_10d": 31.79,
      "change_10d": 3.08,
      "price_20d": 31.84,
      "change_20d": 2.92,
      "ma10": 32.55,
      "ma10_5pct": 30.92,
      "status": "觀察中",
      "alert": "OBS",
      "dist_ma10": 0.68,
      "rsi": 67.1,
      "day_high": 32.96,
      "day_low": 32.42,
      "vol_today": 1775390,
      "vol_avg": 2386656,
      "vol_ratio": 0.74,
      "w52_high": 33.07,
      "w52_low": 24.18,
      "pe": 36.01,
      "mkt_cap": null,
      "day1_price": 32.63,
      "day1_change": 0.0,
      "day2_price": 32.63,
      "day2_change": 0.28,
      "day3_price": 32.54,
      "day3_change": -0.12,
      "day4_price": 32.58,
      "day4_change": 0.0,
      "day5_price": 32.58,
      "day5_change": 0.43,
      "day6_price": 32.44,
      "day6_change": -0.25,
      "day7_price": 32.52,
      "day7_change": -0.09,
      "updated_at": "2026-07-13T09:31:22"
    },
    {
      "symbol": "00935.TW",
      "name": "野村台灣新科技50",
      "current": 58.35,
      "price_10d": 58.95,
      "change_10d": -1.02,
      "price_20d": 58.85,
      "change_20d": -0.85,
      "ma10": 60.58,
      "ma10_5pct": 57.55,
      "status": "觀察中",
      "alert": "OBS",
      "dist_ma10": -3.68,
      "rsi": 32.5,
      "day_high": 60.0,
      "day_low": 57.95,
      "vol_today": 8064667,
      "vol_avg": 18813055,
      "vol_ratio": 0.43,
      "w52_high": 64.2,
      "w52_low": 20.92,
      "pe": 49.35,
      "mkt_cap": null,
      "day1_price": 58.95,
      "day1_change": 0.0,
      "day2_price": 58.95,
      "day2_change": 0.43,
      "day3_price": 58.7,
      "day3_change": -0.25,
      "day4_price": 58.85,
      "day4_change": -4.31,
      "day5_price": 61.5,
      "day5_change": -1.28,
      "day6_price": 62.3,
      "day6_change": -0.72,
      "day7_price": 62.75,
      "day7_change": -0.32,
      "updated_at": "2026-07-13T09:31:22"
    },
    {
      "symbol": "2327.TW",
      "name": "國巨",
      "current": 816.0,
      "price_10d": 1040.0,
      "change_10d": -21.54,
      "price_20d": 855.0,
      "change_20d": -4.56,
      "ma10": 979.7,
      "ma10_5pct": 930.72,
      "status": "觸發加碼",
      "alert": "Alert",
      "dist_ma10": -16.71,
      "rsi": 35.0,
      "day_high": 921.0,
      "day_low": 810.0,
      "vol_today": 71709646,
      "vol_avg": 48779665,
      "vol_ratio": 1.47,
      "w52_high": 1140.0,
      "w52_low": 121.25,
      "pe": 64.3,
      "mkt_cap": "1.68T",
      "day1_price": 900.0,
      "day1_change": 0.0,
      "day2_price": 900.0,
      "day2_change": 1.01,
      "day3_price": 891.0,
      "day3_change": -1.55,
      "day4_price": 905.0,
      "day4_change": -9.95,
      "day5_price": 1005.0,
      "day5_change": -3.83,
      "day6_price": 1045.0,
      "day6_change": -0.95,
      "day7_price": 1055.0,
      "day7_change": -7.46,
      "updated_at": "2026-07-13T09:31:22"
    },
    {
      "symbol": "2377.TW",
      "name": "微星",
      "current": 149.5,
      "price_10d": 139.0,
      "change_10d": 7.55,
      "price_20d": 136.5,
      "change_20d": 9.52,
      "ma10": 143.85,
      "ma10_5pct": 136.66,
      "status": "觀察中",
      "alert": "OBS",
      "dist_ma10": 3.93,
      "rsi": 71.1,
      "day_high": 153.0,
      "day_low": 144.5,
      "vol_today": 29786736,
      "vol_avg": 26341398,
      "vol_ratio": 1.13,
      "w52_high": 149.5,
      "w52_low": 85.0,
      "pe": 22.12,
      "mkt_cap": "126.3B",
      "day1_price": 145.0,
      "day1_change": 0.0,
      "day2_price": 145.0,
      "day2_change": 2.11,
      "day3_price": 142.0,
      "day3_change": 3.65,
      "day4_price": 137.0,
      "day4_change": -3.86,
      "day5_price": 142.5,
      "day5_change": -0.35,
      "day6_price": 143.0,
      "day6_change": 0.0,
      "day7_price": 143.0,
      "day7_change": -1.72,
      "updated_at": "2026-07-13T09:31:22"
    },
    {
      "symbol": "2308.TW",
      "name": "台達電",
      "current": 1890.0,
      "price_10d": 1905.0,
      "change_10d": -0.79,
      "price_20d": 2203.48,
      "change_20d": -14.23,
      "ma10": 1940.5,
      "ma10_5pct": 1843.47,
      "status": "觀察中",
      "alert": "OBS",
      "dist_ma10": -2.6,
      "rsi": 37.8,
      "day_high": 1980.0,
      "day_low": 1885.0,
      "vol_today": 9237915,
      "vol_avg": 11247453,
      "vol_ratio": 0.82,
      "w52_high": 2506.89,
      "w52_low": 470.54,
      "pe": 81.75,
      "mkt_cap": "4.91T",
      "day1_price": 1880.0,
      "day1_change": 0.0,
      "day2_price": 1880.0,
      "day2_change": -0.27,
      "day3_price": 1885.0,
      "day3_change": -0.26,
      "day4_price": 1890.0,
      "day4_change": -5.26,
      "day5_price": 1995.0,
      "day5_change": -3.86,
      "day6_price": 2075.0,
      "day6_change": 5.33,
      "day7_price": 1970.0,
      "day7_change": -1.01,
      "updated_at": "2026-07-13T09:31:22"
    },
    {
      "symbol": "2357.TW",
      "name": "華碩",
      "current": 704.0,
      "price_10d": 660.82,
      "change_10d": 6.53,
      "price_20d": 737.9,
      "change_20d": -4.59,
      "ma10": 675.9,
      "ma10_5pct": 642.1,
      "status": "觀察中",
      "alert": "OBS",
      "dist_ma10": 4.16,
      "rsi": 40.1,
      "day_high": 725.0,
      "day_low": 703.0,
      "vol_today": 6756876,
      "vol_avg": 5820349,
      "vol_ratio": 1.16,
      "w52_high": 875.14,
      "w52_low": 466.24,
      "pe": 11.83,
      "mkt_cap": "522.9B",
      "day1_price": 684.0,
      "day1_change": 0.0,
      "day2_price": 684.0,
      "day2_change": -0.44,
      "day3_price": 687.0,
      "day3_change": 3.62,
      "day4_price": 663.0,
      "day4_change": -2.5,
      "day5_price": 680.0,
      "day5_change": 0.74,
      "day6_price": 675.0,
      "day6_change": 1.2,
      "day7_price": 667.0,
      "day7_change": 1.52,
      "updated_at": "2026-07-13T09:31:22"
    },
    {
      "symbol": "3413.TW",
      "name": "京鼎",
      "current": 334.0,
      "price_10d": 314.0,
      "change_10d": 6.37,
      "price_20d": 307.5,
      "change_20d": 8.62,
      "ma10": 333.05,
      "ma10_5pct": 316.4,
      "status": "觀察中",
      "alert": "OBS",
      "dist_ma10": 0.29,
      "rsi": 63.6,
      "day_high": 342.5,
      "day_low": 329.0,
      "vol_today": 2096084,
      "vol_avg": 2977432,
      "vol_ratio": 0.7,
      "w52_high": 359.22,
      "w52_low": 264.82,
      "pe": 16.1,
      "mkt_cap": "36.9B",
      "day1_price": 334.5,
      "day1_change": 0.0,
      "day2_price": 334.5,
      "day2_change": -1.33,
      "day3_price": 339.0,
      "day3_change": -1.45,
      "day4_price": 344.0,
      "day4_change": 5.68,
      "day5_price": 325.5,
      "day5_change": -0.31,
      "day6_price": 326.5,
      "day6_change": -1.06,
      "day7_price": 330.0,
      "day7_change": -0.6,
      "updated_at": "2026-07-13T09:31:22"
    },
    {
      "symbol": "8996.TW",
      "name": "高力",
      "current": 1240.0,
      "price_10d": 1475.0,
      "change_10d": -15.93,
      "price_20d": 1145.0,
      "change_20d": 8.3,
      "ma10": 1368.0,
      "ma10_5pct": 1299.6,
      "status": "觸發加碼",
      "alert": "Alert",
      "dist_ma10": -9.36,
      "rsi": 35.2,
      "day_high": 1305.0,
      "day_low": 1225.0,
      "vol_today": 1676929,
      "vol_avg": 2647585,
      "vol_ratio": 0.63,
      "w52_high": 1590.0,
      "w52_low": 251.14,
      "pe": 138.08,
      "mkt_cap": "115.2B",
      "day1_price": 1230.0,
      "day1_change": 0.0,
      "day2_price": 1230.0,
      "day2_change": -6.82,
      "day3_price": 1320.0,
      "day3_change": -1.12,
      "day4_price": 1335.0,
      "day4_change": -6.32,
      "day5_price": 1425.0,
      "day5_change": 3.26,
      "day6_price": 1380.0,
      "day6_change": -2.47,
      "day7_price": 1415.0,
      "day7_change": -9.0,
      "updated_at": "2026-07-13T09:31:22"
    },
    {
      "symbol": "7769.TW",
      "name": "鴻勁",
      "current": 6705.0,
      "price_10d": 6395.0,
      "change_10d": 4.85,
      "price_20d": 7210.0,
      "change_20d": -7.0,
      "ma10": 6638.5,
      "ma10_5pct": 6306.57,
      "status": "觀察中",
      "alert": "OBS",
      "dist_ma10": 1.0,
      "rsi": 48.3,
      "day_high": 6995.0,
      "day_low": 6605.0,
      "vol_today": 801421,
      "vol_avg": 674432,
      "vol_ratio": 1.19,
      "w52_high": 8260.0,
      "w52_low": 1296.56,
      "pe": 89.09,
      "mkt_cap": "1.21T",
      "day1_price": 6660.0,
      "day1_change": 0.0,
      "day2_price": 6660.0,
      "day2_change": 9.99,
      "day3_price": 6055.0,
      "day3_change": -2.02,
      "day4_price": 6180.0,
      "day4_change": -9.12,
      "day5_price": 6800.0,
      "day5_change": -0.95,
      "day6_price": 6865.0,
      "day6_change": -2.35,
      "day7_price": 7030.0,
      "day7_change": 1.01,
      "updated_at": "2026-07-13T09:31:22"
    },
    {
      "symbol": "2301.TW",
      "name": "光寶科",
      "current": 222.0,
      "price_10d": 211.5,
      "change_10d": 4.96,
      "price_20d": 217.0,
      "change_20d": 2.3,
      "ma10": 218.2,
      "ma10_5pct": 207.29,
      "status": "觀察中",
      "alert": "OBS",
      "dist_ma10": 1.74,
      "rsi": 49.0,
      "day_high": 232.0,
      "day_low": 218.5,
      "vol_today": 33448517,
      "vol_avg": 31807443,
      "vol_ratio": 1.05,
      "w52_high": 250.0,
      "w52_low": 111.28,
      "pe": 33.64,
      "mkt_cap": "503.7B",
      "day1_price": 213.5,
      "day1_change": 0.0,
      "day2_price": 213.5,
      "day2_change": -0.23,
      "day3_price": 214.0,
      "day3_change": 0.47,
      "day4_price": 213.0,
      "day4_change": -4.91,
      "day5_price": 224.0,
      "day5_change": 2.28,
      "day6_price": 219.0,
      "day6_change": -1.13,
      "day7_price": 221.5,
      "day7_change": 0.91,
      "updated_at": "2026-07-13T09:31:22"
    },
    {
      "symbol": "4958.TW",
      "name": "臻鼎",
      "current": 646.0,
      "price_10d": 573.0,
      "change_10d": 12.74,
      "price_20d": 552.0,
      "change_20d": 17.03,
      "ma10": 595.8,
      "ma10_5pct": 566.01,
      "status": "觀察中",
      "alert": "OBS",
      "dist_ma10": 8.43,
      "rsi": 59.5,
      "day_high": 646.0,
      "day_low": 614.0,
      "vol_today": 72226301,
      "vol_avg": 30284688,
      "vol_ratio": 2.38,
      "w52_high": 646.0,
      "w52_low": 107.76,
      "pe": 95.56,
      "mkt_cap": "697.3B",
      "day1_price": 588.0,
      "day1_change": 0.0,
      "day2_price": 588.0,
      "day2_change": 4.07,
      "day3_price": 565.0,
      "day3_change": 3.1,
      "day4_price": 548.0,
      "day4_change": -5.35,
      "day5_price": 579.0,
      "day5_change": -5.55,
      "day6_price": 613.0,
      "day6_change": 2.51,
      "day7_price": 598.0,
      "day7_change": -0.83,
      "updated_at": "2026-07-13T09:31:22"
    },
    {
      "symbol": "2383.TW",
      "name": "台光電",
      "current": 5125.0,
      "price_10d": 5450.0,
      "change_10d": -5.96,
      "price_20d": 4830.0,
      "change_20d": 6.11,
      "ma10": 5438.5,
      "ma10_5pct": 5166.57,
      "status": "觀察中",
      "alert": "Alert",
      "dist_ma10": -5.76,
      "rsi": 39.3,
      "day_high": 5390.0,
      "day_low": 5055.0,
      "vol_today": 1873968,
      "vol_avg": 2014928,
      "vol_ratio": 0.93,
      "w52_high": 6080.0,
      "w52_low": 915.98,
      "pe": 111.24,
      "mkt_cap": "1.84T",
      "day1_price": 5295.0,
      "day1_change": 0.0,
      "day2_price": 5295.0,
      "day2_change": -0.38,
      "day3_price": 5315.0,
      "day3_change": 1.82,
      "day4_price": 5220.0,
      "day4_change": -4.66,
      "day5_price": 5475.0,
      "day5_change": -9.95,
      "day6_price": 6080.0,
      "day6_change": 7.52,
      "day7_price": 5655.0,
      "day7_change": 2.17,
      "updated_at": "2026-07-13T09:31:22"
    },
    {
      "symbol": "2404.TW",
      "name": "漢唐",
      "current": 1230.0,
      "price_10d": 1360.0,
      "change_10d": -9.56,
      "price_20d": 1310.0,
      "change_20d": -6.11,
      "ma10": 1279.5,
      "ma10_5pct": 1215.52,
      "status": "觀察中",
      "alert": "OBS",
      "dist_ma10": -3.87,
      "rsi": 47.1,
      "day_high": 1245.0,
      "day_low": 1205.0,
      "vol_today": 1587856,
      "vol_avg": 3750443,
      "vol_ratio": 0.42,
      "w52_high": 1385.0,
      "w52_low": 695.08,
      "pe": 25.76,
      "mkt_cap": "232.3B",
      "day1_price": 1215.0,
      "day1_change": 0.0,
      "day2_price": 1215.0,
      "day2_change": 1.25,
      "day3_price": 1200.0,
      "day3_change": -4.76,
      "day4_price": 1260.0,
      "day4_change": -4.55,
      "day5_price": 1320.0,
      "day5_change": -2.22,
      "day6_price": 1350.0,
      "day6_change": -2.53,
      "day7_price": 1385.0,
      "day7_change": 6.54,
      "updated_at": "2026-07-13T09:31:22"
    },
    {
      "symbol": "2408.TW",
      "name": "南亞科",
      "current": 423.0,
      "price_10d": 451.55,
      "change_10d": -6.32,
      "price_20d": 372.8,
      "change_20d": 13.47,
      "ma10": 419.67,
      "ma10_5pct": 398.69,
      "status": "觀察中",
      "alert": "OBS",
      "dist_ma10": 0.79,
      "rsi": 42.9,
      "day_high": 466.5,
      "day_low": 420.5,
      "vol_today": 130256509,
      "vol_avg": 115713777,
      "vol_ratio": 1.13,
      "w52_high": 503.38,
      "w52_low": 40.42,
      "pe": 39.17,
      "mkt_cap": "1.31T",
      "day1_price": 435.5,
      "day1_change": 0.0,
      "day2_price": 435.5,
      "day2_change": 9.97,
      "day3_price": 396.0,
      "day3_change": -1.74,
      "day4_price": 403.0,
      "day4_change": -3.85,
      "day5_price": 419.15,
      "day5_change": 2.69,
      "day6_price": 408.19,
      "day6_change": 0.61,
      "day7_price": 405.7,
      "day7_change": -3.32,
      "updated_at": "2026-07-13T09:31:22"
    },
    {
      "symbol": "3037.TW",
      "name": "欣興",
      "current": 903.0,
      "price_10d": 974.01,
      "change_10d": -7.29,
      "price_20d": 900.16,
      "change_20d": 0.32,
      "ma10": 932.27,
      "ma10_5pct": 885.66,
      "status": "觀察中",
      "alert": "OBS",
      "dist_ma10": -3.14,
      "rsi": 43.9,
      "day_high": 948.0,
      "day_low": 892.0,
      "vol_today": 33666186,
      "vol_avg": 25212259,
      "vol_ratio": 1.34,
      "w52_high": 1082.78,
      "w52_low": 119.75,
      "pe": 206.16,
      "mkt_cap": "1.42T",
      "day1_price": 875.0,
      "day1_change": 0.0,
      "day2_price": 875.0,
      "day2_change": 1.39,
      "day3_price": 863.0,
      "day3_change": 2.74,
      "day4_price": 840.0,
      "day4_change": -8.4,
      "day5_price": 917.0,
      "day5_change": -5.17,
      "day6_price": 967.02,
      "day6_change": -1.02,
      "day7_price": 977.0,
      "day7_change": -5.86,
      "updated_at": "2026-07-13T09:31:22"
    },
    {
      "symbol": "2313.TW",
      "name": "華通",
      "current": 235.0,
      "price_10d": 221.0,
      "change_10d": 6.33,
      "price_20d": 263.0,
      "change_20d": -10.65,
      "ma10": 226.85,
      "ma10_5pct": 215.51,
      "status": "觀察中",
      "alert": "OBS",
      "dist_ma10": 3.59,
      "rsi": 45.9,
      "day_high": 245.0,
      "day_low": 225.0,
      "vol_today": 64001855,
      "vol_avg": 52844707,
      "vol_ratio": 1.21,
      "w52_high": 295.55,
      "w52_low": 60.4,
      "pe": 43.04,
      "mkt_cap": "281.7B",
      "day1_price": 223.0,
      "day1_change": 0.0,
      "day2_price": 223.0,
      "day2_change": -0.45,
      "day3_price": 224.0,
      "day3_change": 2.75,
      "day4_price": 218.0,
      "day4_change": -7.23,
      "day5_price": 235.0,
      "day5_change": 2.4,
      "day6_price": 229.5,
      "day6_change": 0.44,
      "day7_price": 228.5,
      "day7_change": 3.86,
      "updated_at": "2026-07-13T09:31:22"
    },
    {
      "symbol": "2912.TW",
      "name": "統一超",
      "current": 239.5,
      "price_10d": 224.0,
      "change_10d": 6.92,
      "price_20d": 230.0,
      "change_20d": 4.13,
      "ma10": 234.85,
      "ma10_5pct": 223.11,
      "status": "觀察中",
      "alert": "OBS",
      "dist_ma10": 1.98,
      "rsi": 72.7,
      "day_high": 244.0,
      "day_low": 239.0,
      "vol_today": 2346026,
      "vol_avg": 5909249,
      "vol_ratio": 0.4,
      "w52_high": 260.0,
      "w52_low": 206.5,
      "pe": 22.28,
      "mkt_cap": "249.0B",
      "day1_price": 241.0,
      "day1_change": 0.0,
      "day2_price": 241.0,
      "day2_change": 0.0,
      "day3_price": 241.0,
      "day3_change": 0.42,
      "day4_price": 240.0,
      "day4_change": 0.0,
      "day5_price": 240.0,
      "day5_change": 3.9,
      "day6_price": 231.0,
      "day6_change": 1.09,
      "day7_price": 228.5,
      "day7_change": 2.24,
      "updated_at": "2026-07-13T09:31:22"
    },
    {
      "symbol": "006208.TW",
      "name": "富邦台灣采吉50",
      "current": 246.75,
      "price_10d": 242.75,
      "change_10d": 1.65,
      "price_20d": 236.1,
      "change_20d": 4.51,
      "ma10": 248.96,
      "ma10_5pct": 236.51,
      "status": "觀察中",
      "alert": "OBS",
      "dist_ma10": -0.89,
      "rsi": 40.5,
      "day_high": 249.7,
      "day_low": 245.65,
      "vol_today": 4158377,
      "vol_avg": 3868997,
      "vol_ratio": 1.07,
      "w52_high": 257.45,
      "w52_low": 111.65,
      "pe": 34.74,
      "mkt_cap": null,
      "day1_price": 245.7,
      "day1_change": 0.0,
      "day2_price": 245.7,
      "day2_change": -0.18,
      "day3_price": 246.15,
      "day3_change": -0.14,
      "day4_price": 246.5,
      "day4_change": -1.93,
      "day5_price": 251.35,
      "day5_change": 0.0,
      "day6_price": 251.35,
      "day6_change": -0.38,
      "day7_price": 252.3,
      "day7_change": -0.53,
      "updated_at": "2026-07-13T09:31:22"
    },
    {
      "symbol": "3481.TW",
      "name": "群創",
      "current": 61.0,
      "price_10d": 67.0,
      "change_10d": -8.96,
      "price_20d": 48.55,
      "change_20d": 25.64,
      "ma10": 65.99,
      "ma10_5pct": 62.69,
      "status": "觀察中",
      "alert": "Alert",
      "dist_ma10": -7.56,
      "rsi": 42.0,
      "day_high": 67.2,
      "day_low": 60.5,
      "vol_today": 396641650,
      "vol_avg": 540203094,
      "vol_ratio": 0.73,
      "w52_high": 70.9,
      "w52_low": 10.75,
      "pe": 2033.33,
      "mkt_cap": "486.8B",
      "day1_price": 65.3,
      "day1_change": 0.0,
      "day2_price": 65.3,
      "day2_change": 0.15,
      "day3_price": 65.2,
      "day3_change": 1.56,
      "day4_price": 64.2,
      "day4_change": -7.23,
      "day5_price": 69.2,
      "day5_change": 4.85,
      "day6_price": 66.0,
      "day6_change": -2.37,
      "day7_price": 67.6,
      "day7_change": 0.3,
      "updated_at": "2026-07-13T09:31:22"
    },
    {
      "symbol": "3211.TWO",
      "name": "順達",
      "current": 457.5,
      "price_10d": 381.47,
      "change_10d": 19.93,
      "price_20d": 406.25,
      "change_20d": 12.62,
      "ma10": 420.99,
      "ma10_5pct": 399.94,
      "status": "觀察中",
      "alert": "OBS",
      "dist_ma10": 8.67,
      "rsi": 60.4,
      "day_high": 495.0,
      "day_low": 449.5,
      "vol_today": 15498118,
      "vol_avg": 9122536,
      "vol_ratio": 1.7,
      "w52_high": 457.5,
      "w52_low": 210.42,
      "pe": 50.89,
      "mkt_cap": "70.6B",
      "day1_price": 454.0,
      "day1_change": 0.0,
      "day2_price": 454.0,
      "day2_change": 6.2,
      "day3_price": 427.5,
      "day3_change": 9.9,
      "day4_price": 389.0,
      "day4_change": -7.93,
      "day5_price": 422.5,
      "day5_change": 5.36,
      "day6_price": 401.0,
      "day6_change": -1.35,
      "day7_price": 406.5,
      "day7_change": 2.51,
      "updated_at": "2026-07-13T09:31:22"
    },
    {
      "symbol": "8299.TWO",
      "name": "群聯",
      "current": 2170.0,
      "price_10d": 2323.04,
      "change_10d": -6.59,
      "price_20d": 2293.25,
      "change_20d": -5.37,
      "ma10": 2237.5,
      "ma10_5pct": 2125.62,
      "status": "觀察中",
      "alert": "OBS",
      "dist_ma10": -3.02,
      "rsi": 35.5,
      "day_high": 2275.0,
      "day_low": 2155.0,
      "vol_today": 2909144,
      "vol_avg": 5753251,
      "vol_ratio": 0.51,
      "w52_high": 2859.12,
      "w52_low": 464.01,
      "pe": 54.6,
      "mkt_cap": "479.8B",
      "day1_price": 2220.0,
      "day1_change": 0.0,
      "day2_price": 2220.0,
      "day2_change": 3.74,
      "day3_price": 2140.0,
      "day3_change": -0.23,
      "day4_price": 2145.0,
      "day4_change": -6.33,
      "day5_price": 2290.0,
      "day5_change": -0.22,
      "day6_price": 2295.0,
      "day6_change": 2.46,
      "day7_price": 2240.0,
      "day7_change": -1.32,
      "updated_at": "2026-07-13T09:31:22"
    },
    {
      "symbol": "3680.TWO",
      "name": "家登",
      "current": 523.0,
      "price_10d": 489.0,
      "change_10d": 6.95,
      "price_20d": 503.0,
      "change_20d": 3.98,
      "ma10": 521.9,
      "ma10_5pct": 495.8,
      "status": "觀察中",
      "alert": "OBS",
      "dist_ma10": 0.21,
      "rsi": 46.7,
      "day_high": 533.0,
      "day_low": 490.5,
      "vol_today": 2621593,
      "vol_avg": 1925781,
      "vol_ratio": 1.36,
      "w52_high": 610.77,
      "w52_low": 279.04,
      "pe": 55.82,
      "mkt_cap": "50.2B",
      "day1_price": 496.0,
      "day1_change": 0.0,
      "day2_price": 496.0,
      "day2_change": -1.2,
      "day3_price": 502.0,
      "day3_change": -0.99,
      "day4_price": 507.0,
      "day4_change": -5.23,
      "day5_price": 535.0,
      "day5_change": -0.74,
      "day6_price": 539.0,
      "day6_change": -2.88,
      "day7_price": 555.0,
      "day7_change": -0.54,
      "updated_at": "2026-07-13T09:31:22"
    },
    {
      "symbol": "5274.TWO",
      "name": "信驊",
      "current": 13520.0,
      "price_10d": 13827.27,
      "change_10d": -2.22,
      "price_20d": 16691.2,
      "change_20d": -19.0,
      "ma10": 14644.45,
      "ma10_5pct": 13912.23,
      "status": "觀察中",
      "alert": "Alert",
      "dist_ma10": -7.68,
      "rsi": 29.4,
      "day_high": 14865.0,
      "day_low": 13070.0,
      "vol_today": 317285,
      "vol_avg": 269017,
      "vol_ratio": 1.18,
      "w52_high": 17442.28,
      "w52_low": 3972.59,
      "pe": 143.39,
      "mkt_cap": "562.2B",
      "day1_price": 13665.0,
      "day1_change": 0.0,
      "day2_price": 13665.0,
      "day2_change": -2.22,
      "day3_price": 13975.0,
      "day3_change": -3.05,
      "day4_price": 14415.0,
      "day4_change": -2.54,
      "day5_price": 14790.91,
      "day5_change": -5.76,
      "day6_price": 15695.45,
      "day6_change": -2.73,
      "day7_price": 16136.36,
      "day7_change": 3.53,
      "updated_at": "2026-07-13T09:31:22"
    },
    {
      "symbol": "4979.TWO",
      "name": "華星光",
      "current": 419.0,
      "price_10d": 456.5,
      "change_10d": -8.21,
      "price_20d": 501.0,
      "change_20d": -16.37,
      "ma10": 444.15,
      "ma10_5pct": 421.94,
      "status": "觀察中",
      "alert": "Alert",
      "dist_ma10": -5.66,
      "rsi": 23.6,
      "day_high": 451.0,
      "day_low": 413.5,
      "vol_today": 4475866,
      "vol_avg": 5295436,
      "vol_ratio": 0.85,
      "w52_high": 718.0,
      "w52_low": 179.0,
      "pe": 78.76,
      "mkt_cap": "59.1B",
      "day1_price": 432.5,
      "day1_change": 0.0,
      "day2_price": 432.5,
      "day2_change": -0.46,
      "day3_price": 434.5,
      "day3_change": 1.52,
      "day4_price": 428.0,
      "day4_change": -6.35,
      "day5_price": 457.0,
      "day5_change": -2.45,
      "day6_price": 468.5,
      "day6_change": 5.28,
      "day7_price": 445.0,
      "day7_change": -1.22,
      "updated_at": "2026-07-13T09:31:22"
    },
    {
      "symbol": "1785.TWO",
      "name": "光陽科",
      "current": 129.0,
      "price_10d": 140.5,
      "change_10d": -8.19,
      "price_20d": 141.5,
      "change_20d": -8.83,
      "ma10": 144.65,
      "ma10_5pct": 137.42,
      "status": "觀察中",
      "alert": "Alert",
      "dist_ma10": -10.82,
      "rsi": 35.3,
      "day_high": 135.0,
      "day_low": 129.0,
      "vol_today": 28424048,
      "vol_avg": 21639895,
      "vol_ratio": 1.31,
      "w52_high": 185.0,
      "w52_low": 50.0,
      "pe": 41.21,
      "mkt_cap": "76.9B",
      "day1_price": 143.0,
      "day1_change": 0.0,
      "day2_price": 143.0,
      "day2_change": -0.35,
      "day3_price": 143.5,
      "day3_change": 2.14,
      "day4_price": 140.5,
      "day4_change": -8.17,
      "day5_price": 153.0,
      "day5_change": -1.92,
      "day6_price": 156.0,
      "day6_change": 2.63,
      "day7_price": 152.0,
      "day7_change": 7.04,
      "updated_at": "2026-07-13T09:31:22"
    },
    {
      "symbol": "5347.TWO",
      "name": "世界",
      "current": 178.5,
      "price_10d": 203.68,
      "change_10d": -12.36,
      "price_20d": 165.58,
      "change_20d": 7.8,
      "ma10": 185.42,
      "ma10_5pct": 176.15,
      "status": "觸發加碼",
      "alert": "OBS",
      "dist_ma10": -3.73,
      "rsi": 48.3,
      "day_high": 187.0,
      "day_low": 176.0,
      "vol_today": 28808532,
      "vol_avg": 33004043,
      "vol_ratio": 0.87,
      "w52_high": 214.91,
      "w52_low": 85.97,
      "pe": 42.3,
      "mkt_cap": "335.3B",
      "day1_price": 173.0,
      "day1_change": 0.0,
      "day2_price": 173.0,
      "day2_change": -1.98,
      "day3_price": 176.5,
      "day3_change": 0.86,
      "day4_price": 175.0,
      "day4_change": -5.41,
      "day5_price": 185.0,
      "day5_change": -2.13,
      "day6_price": 189.03,
      "day6_change": -2.27,
      "day7_price": 193.42,
      "day7_change": -3.18,
      "updated_at": "2026-07-13T09:31:22"
    },
    {
      "symbol": "3293.TWO",
      "name": "鈊象",
      "current": 729.0,
      "price_10d": 733.05,
      "change_10d": -0.55,
      "price_20d": 719.7,
      "change_20d": 1.29,
      "ma10": 751.1,
      "ma10_5pct": 713.54,
      "status": "觀察中",
      "alert": "OBS",
      "dist_ma10": -2.94,
      "rsi": 51.3,
      "day_high": 750.0,
      "day_low": 728.0,
      "vol_today": 1469494,
      "vol_avg": 2441916,
      "vol_ratio": 0.6,
      "w52_high": 803.59,
      "w52_low": 638.68,
      "pe": 19.25,
      "mkt_cap": "205.4B",
      "day1_price": 744.0,
      "day1_change": 0.0,
      "day2_price": 744.0,
      "day2_change": -0.53,
      "day3_price": 748.0,
      "day3_change": 1.91,
      "day4_price": 734.0,
      "day4_change": -3.02,
      "day5_price": 756.88,
      "day5_change": -0.38,
      "day6_price": 759.74,
      "day6_change": -0.38,
      "day7_price": 762.6,
      "day7_change": -2.32,
      "updated_at": "2026-07-13T09:31:22"
    },
    {
      "symbol": "4541.TWO",
      "name": "晟田",
      "current": 67.1,
      "price_10d": 47.25,
      "change_10d": 42.01,
      "price_20d": 46.18,
      "change_20d": 45.3,
      "ma10": 60.18,
      "ma10_5pct": 57.17,
      "status": "觀察中",
      "alert": "OBS",
      "dist_ma10": 11.5,
      "rsi": 76.2,
      "day_high": 67.1,
      "day_low": 62.8,
      "vol_today": 7057861,
      "vol_avg": 3337441,
      "vol_ratio": 2.11,
      "w52_high": 67.1,
      "w52_low": 38.17,
      "pe": 33.22,
      "mkt_cap": "4.5B",
      "day1_price": 61.0,
      "day1_change": 0.0,
      "day2_price": 61.0,
      "day2_change": 0.99,
      "day3_price": 60.4,
      "day3_change": -1.15,
      "day4_price": 61.1,
      "day4_change": -8.4,
      "day5_price": 66.7,
      "day5_change": 9.88,
      "day6_price": 60.7,
      "day6_change": 9.96,
      "day7_price": 55.2,
      "day7_change": -2.65,
      "updated_at": "2026-07-13T09:31:22"
    },
    {
      "symbol": "4931.TWO",
      "name": "新盛力",
      "current": 237.0,
      "price_10d": 230.04,
      "change_10d": 3.03,
      "price_20d": 233.5,
      "change_20d": 1.5,
      "ma10": 247.15,
      "ma10_5pct": 234.79,
      "status": "觀察中",
      "alert": "OBS",
      "dist_ma10": -4.11,
      "rsi": 42.3,
      "day_high": 264.5,
      "day_low": 233.5,
      "vol_today": 8481010,
      "vol_avg": 10749891,
      "vol_ratio": 0.79,
      "w52_high": 276.54,
      "w52_low": 94.5,
      "pe": 76.21,
      "mkt_cap": "15.5B",
      "day1_price": 255.0,
      "day1_change": 0.0,
      "day2_price": 255.0,
      "day2_change": -6.25,
      "day3_price": 272.0,
      "day3_change": 9.9,
      "day4_price": 247.5,
      "day4_change": -5.17,
      "day5_price": 261.0,
      "day5_change": 9.89,
      "day6_price": 237.5,
      "day6_change": 0.42,
      "day7_price": 236.5,
      "day7_change": 1.28,
      "updated_at": "2026-07-13T09:31:22"
    }
  ]
}